{"stat.useItem.minecraft.bow":690,"stat.pickup.iceandfire.fire_dragon_flesh":6,"stat.leaveGame":17,"stat.drop.minecraft.gunpowder":1,"stat.pickup.extrautils2.redorchid":3,"stat.pickup.tconstruct.edible":7,"stat.pickup.ebwizardry.spell_book":2,"stat.mineBlock.rustic.leaves":31,"stat.pickup.harvestcraft.shadedgarden":6,"stat.useItem.minecraft.glowstone":175,"stat.mineBlock.minecraft.sandstone":19,"stat.craftItem.minecraft.ender_eye":1,"stat.craftItem.chesttransporter.chesttransporter_iron":1,"stat.killEntity.PigZombie":2,"stat.pickup.tconstruct.faucet":5,"stat.mineBlock.harvestcraft.beehive":1,"stat.mineBlock.taiga.meteorite_block":6,"stat.useItem.chesttransporter.chesttransporter_diamond":22,"stat.mineBlock.tconstruct.lavawood_stairs":5,"stat.mineBlock.taiga.meteoritecobble_block":8,"stat.pickup.harvestcraft.calamarirawitem":2,"stat.mineBlock.minecraft.red_sandstone":2,"stat.drop.minecraft.iron_sword":1,"stat.pickup.tconstruct.scythe_head":1,"stat.pickup.minecraft.rotten_flesh":65,"stat.pickup.minecraft.brick_block":2,"stat.craftItem.minecraft.stone_axe":1,"stat.pickup.iceandfire.witherbone":2,"stat.useItem.harvestcraft.bananaitem":2,"stat.killEntity.Enderman":5,"stat.mineBlock.culinaryconstruct.sandwich_station":1,"stat.pickup.minecraft.leather_boots":3,"stat.pickup.biomesoplenty.mushroom":2,"stat.pickup.minecraft.brown_mushroom":1,"stat.mineBlock.tconstruct.slime_vine_purple":1,"stat.killEntity.Witch":2,"stat.mineBlock.rustic.log":16,"stat.useItem.minecraft.iron_pickaxe":835,"stat.pickup.minecraft.stained_hardened_clay":6,"stat.craftItem.minecraft.wooden_pickaxe":1,"stat.useItem.minecraft.iron_shovel":207,"stat.drop.minecraft.chainmail_leggings":1,"stat.mineBlock.minecraft.brick_block":2,"stat.pickup.minecraft.double_plant":5,"stat.drop.extrautils2.itembuilderswand":1,"stat.craftItem.minecraft.bed":1,"stat.craftItem.minecraft.glass_pane":16,"stat.pickup.harvestcraft.onionitem":11,"stat.mineBlock.chisel.marble2":22,"stat.mineBlock.minecraft.hopper":6,"stat.mineBlock.minecraft.vine":5,"stat.pickup.thermalfoundation.material":6,"stat.pickup.rustic.wildberries":11,"stat.furnaceInteraction":32,"stat.pickup.harvestcraft.cherryitem":1,"stat.killEntity.ZombieVillager":5,"stat.pickup.harvestcraft.cornitem":4,"stat.mineBlock.harvestcraft.pambanana":1,"stat.pickup.extrautils2.enderlilly":1,"stat.pickup.minecraft.nether_brick":129,"stat.drop.minecraft.red_flower":4,"stat.craftItem.extrautils2.decorativesolidwood":1,"stat.useItem.flammpfeil.slashblade.slashbladenamed":13,"stat.pickup.minecraft.beef":1,"stat.craftItem.mysticalagriculture.crafting":59,"stat.pickup.extrautils2.decorativesolidwood":29,"stat.mineBlock.minecraft.stained_hardened_clay":5,"stat.pickup.biomesoplenty.flower_0":21,"stat.mineBlock.chisel.planks-dark-oak":5,"stat.useItem.rustic.wildberries":8,"stat.mineBlock.harvestcraft.pamcinnamon":3,"stat.pickup.mysticalagriculture.tier1_inferium_seeds":99,"stat.mineBlock.tconstruct.ore":12,"stat.useItem.minecraft.dark_oak_door":3,"stat.pickup.tombstone.gift":2,"stat.pickup.minecraft.potion":1,"stat.pickup.culinaryconstruct.sandwich":64,"stat.useItem.minecraft.flint_and_steel":1,"stat.pickup.tconstruct.smeltery_io":5,"stat.useItem.croparia.fruit_rawbeef":1,"stat.killEntity.Husk":1,"stat.craftItem.securitycraft.laser_block":1,"stat.useItem.rustic.chili_pepper":1,"stat.mineBlock.rustic.crop_stake":2,"stat.drop.chisel.quartz1":2,"stat.deaths":56,"stat.useItem.tconstruct.smeltery_io":7,"stat.pickup.minecraft.egg":8,"stat.useItem.minecraft.nether_brick":48,"stat.pickup.minecraft.glass_pane":70,"stat.pickup.taiga.meteorite_block":6,"stat.drop.minecraft.iron_ingot":2,"stat.pickup.chisel.marble2":7,"stat.killEntity.thermalfoundation.blitz":1,"stat.mineBlock.minecraft.tallgrass":292,"stat.pickup.tconstruct.seared":527,"stat.chestOpened":219,"stat.useItem.croparia.fruit_redstone":2,"stat.useItem.minecraft.stone":91,"stat.mineBlock.rustic.chamomile":4,"stat.pickup.minecraft.arrow":43,"stat.pickup.minecraft.iron_sword":2,"stat.pickup.iceandfire.blindfold":1,"stat.killEntity.Ghast":1,"stat.pickup.minecraft.gold_nugget":63,"stat.craftItem.minecraft.coal":2,"stat.pickup.harvestcraft.chilipepperitem":4,"stat.drop.minecraft.iron_pickaxe":1,"stat.drop.fossil.gold_javelin":1,"stat.pickup.chisel.basalt2":2,"stat.pickup.minecraft.carrot":35,"stat.crouchOneCm":253523,"stat.mineBlock.minecraft.chest":22,"stat.craftItem.minecraft.diamond":10,"stat.craftItem.minecraft.iron_ingot":20,"stat.pickup.rustic.grape_stem":1,"stat.craftItem.minecraft.hopper":1,"stat.craftingTableInteraction":119,"stat.craftItem.extrautils2.decorativesolid":32,"stat.pickup.minecraft.nether_brick_fence":1,"stat.pickup.iceandfire.ice_dragon_flesh":7,"stat.craftItem.tconstruct.pattern":26,"stat.pickup.minecraft.wooden_pickaxe":2,"stat.mineBlock.minecraft.log2":55,"stat.mineBlock.fossil.figurine":1,"stat.mineBlock.tconstruct.smeltery_io":5,"stat.mineBlock.biomesoplenty.plant_1":1,"stat.mineBlock.biomesoplenty.plant_0":516,"stat.pickup.minecraft.dye":4,"stat.pickup.minecraft.planks":128,"stat.pickup.chisel.limestone2":9,"stat.pickup.minecraft.wheat_seeds":81,"stat.mineBlock.biomesoplenty.gem_ore":18,"stat.drop.mysticalagriculture.crafting":4,"stat.mineBlock.fossil.volcanic_rock":35,"stat.craftItem.extrautils2.pipe":64,"stat.pickup.harvestcraft.cinnamonitem":1,"stat.mineBlock.minecraft.dirt":13317,"stat.craftItem.ironfurnaces.obsidian_furnace_idle":1,"stat.pickup.tconstruct.pattern":1,"stat.useItem.minecraft.bread":57,"stat.craftItem.improvableskills.skills_book":1,"stat.mineBlock.biomesoplenty.leaves_5":1,"stat.mineBlock.iceandfire.silver_ore":5,"stat.useItem.minecraft.cobblestone":428,"stat.useItem.minecraft.gravel":24,"stat.mineBlock.minecraft.double_plant":17,"stat.pickup.tconstruct.pickaxe":3,"stat.pickup.biomesoplenty.biome_essence":157,"stat.pickup.harvestcraft.hazelnutitem":6,"stat.pickup.rustic.vanta_lily":5,"stat.drop.minecraft.chicken":4,"stat.pickup.minecraft.iron_pickaxe":2,"stat.useItem.tconstruct.pickaxe":21535,"stat.craftItem.minecraft.gold_ingot":28,"stat.pickup.minecraft.chicken":4,"stat.craftItem.torcherino.blockdoublecompressedtorcherino":2,"stat.pickup.minecraft.apple":2,"stat.pickup.morebuckets.diamond_bucket":1,"stat.craftItem.minecraft.bucket":9,"stat.craftItem.minecraft.planks":2804,"stat.useItem.minecraft.iron_sword":154,"stat.pickup.torchmaster.mega_torch":12,"stat.pickup.biomesoplenty.berries":12,"stat.drop.biomesoplenty.flower_0":2,"stat.craftItem.torcherino.blocktorcherino":3,"stat.craftItem.rustic.fertile_soil":32,"stat.useItem.minecraft.stonebrick":33,"stat.pickup.minecraft.book":167,"stat.mineBlock.minecraft.log":613,"stat.craftItem.tconstruct.seared_slab":6,"stat.pickup.iceandfire.dragonbone":52,"stat.pickup.biomesoplenty.dirt":12,"stat.pickup.minecraft.red_flower":12,"stat.pickup.minecraft.wool":17,"stat.useItem.chiselsandbits.tape_measure":49,"stat.craftItem.chesttransporter.chesttransporter_diamond":3,"stat.craftItem.minecraft.cobblestone":18,"stat.pickup.minecraft.red_sandstone_stairs":1,"stat.mineBlock.securitycraft.reinforced_stone_brick":32,"stat.cakeSlicesEaten":15,"stat.pickup.fossil.fossil_seed_fern":4,"stat.craftItem.extrautils2.itembuilderswand":1,"stat.pickup.fossil.biofossil":46,"stat.useItem.minecraft.iron_axe":167,"stat.pickup.croparia.seed_crop_rawbeef":5,"stat.mineBlock.minecraft.cobblestone":188,"stat.craftItem.tconstruct.edible":8,"stat.mineBlock.minecraft.pumpkin":8,"stat.pickup.torcherino.blockdoublecompressedtorcherino":28,"stat.killEntity.gorgon":1,"stat.pickup.iceandfire.ice_dragon_heart":1,"stat.pickup.minecraft.flint":11,"stat.mineBlock.minecraft.yellow_flower":1,"stat.craftItem.tombstone.grave_key":16,"stat.pickup.minecraft.leather_chestplate":3,"stat.craftItem.tconstruct.firewood_stairs":8,"stat.mineBlock.minecraft.concrete":33,"stat.craftItem.minecraft.wool":7,"stat.mineBlock.minecraft.stained_glass_pane":24,"stat.craftItem.minecraft.clock":15,"stat.useItem.minecraft.concrete_powder":31,"stat.pickup.minecraft.enchanted_book":3,"stat.pickup.minecraft.glowstone":6,"stat.drop.minecraft.cobblestone":151,"stat.mineBlock.fossil.vase_amphora":1,"stat.useItem.openblocks.elevator":2,"stat.useItem.minecraft.obsidian":13,"stat.mineBlock.ironchest.iron_chest":2,"stat.useItem.minecraft.stone_slab2":211,"stat.pickup.croparia.seed_crop_coal":38,"stat.pickup.minecraft.bow":1,"stat.pickup.forge.bucketfilled":1,"stat.craftItem.minecraft.dark_oak_door":3,"stat.craftItem.minecraft.furnace":15,"stat.drop.harvestcraft.onionitem":2,"stat.pickup.thermalfoundation.ore":48,"stat.useItem.minecraft.egg":1,"stat.mineBlock.fossil.permafrost":23,"stat.mineBlock.minecraft.obsidian":11,"stat.mineBlock.minecraft.clay":30,"stat.pickup.minecraft.diamond_leggings":1,"stat.useItem.minecraft.brick_block":1,"stat.flyOneCm":12223933,"stat.drop.minecraft.iron_helmet":1,"stat.pickup.minecraft.sandstone":17,"stat.pickup.rustic.chili_pepper":1,"stat.craftItem.extrautils2.passivegenerator":2,"stat.pickup.rustic.slate":38,"stat.drop.morebuckets.diamond_bucket":3,"stat.craftItem.minecraft.stained_glass":40,"stat.timeSinceDeath":106589,"stat.useItem.morebuckets.diamond_bucket":491,"stat.craftItem.minecraft.iron_block":11,"stat.pickup.ebwizardry.arcane_workbench":1,"stat.useItem.chesttransporter.chesttransporter_iron":3,"stat.craftItem.minecraft.stonebrick":60,"stat.pickup.harvestcraft.whitemushroomitem":4,"stat.pickup.travelersbackpack.travelers_backpack":7,"stat.craftItem.tconstruct.seared":56,"stat.mineBlock.minecraft.coal_ore":392,"tombstone:tomb_raiding":1,"stat.pickup.culinaryconstruct.sandwich_station":1,"stat.drop.minecraft.wool":1,"stat.pickup.minecraft.shield":3,"stat.killEntity.Creeper":10,"stat.talkedToVillager":92,"stat.pickup.extrautils2.ingredients":4,"stat.useItem.croparia.fruit_lapis":1,"stat.mineBlock.minecraft.red_mushroom_block":42,"stat.pickup.minecraft.string":19,"stat.craftItem.biomesoplenty.biome_finder":2,"stat.mineBlock.rustic.vanta_lily":1,"stat.mineBlock.tconstruct.firewood_stairs":3,"stat.pickup.tombstone.crafting_ingredient":10,"stat.entityKilledBy.Skeleton":6,"stat.craftItem.tconstruct.tooltables":5,"stat.killEntity.Squid":2,"stat.sprintOneCm":2732105,"stat.useItem.minecraft.diamond_shovel":24,"stat.mineBlock.biomesoplenty.flower_0":8,"stat.mineBlock.minecraft.stone_slab":20,"stat.drop.minecraft.dark_oak_door":1,"stat.mineBlock.biomesoplenty.grass":46,"stat.killEntity.ebwizardry:evil_wizard":1,"stat.drop.tp.pouch":3,"stat.pickup.extrautils2.passivegenerator":4,"stat.mineBlock.rustic.wildberry_bush":16,"stat.useItem.tconstruct.seared_stairs_brick":63,"stat.drop.tconstruct.cleaver":1,"stat.mineBlock.minecraft.diamond_ore":5,"stat.mineBlock.harvestcraft.pamapple":1,"stat.mineBlock.biomesoplenty.mushroom":2,"stat.pickup.fossil.relic_scrap":42,"stat.pickup.croparia.fruit_rawbeef":5,"stat.pickup.minecraft.leather_leggings":1,"stat.useItem.tconstruct.seared_tank":1,"stat.pickup.harvestcraft.mustardseedsitem":3,"stat.craftItem.croparia.seed_crop_redstone":1,"stat.useItem.culinaryconstruct.sandwich":56,"stat.pickup.harvestcraft.flaxitem":4,"stat.pickup.ebwizardry.ruined_spell_book":1,"stat.pickup.tconstruct.ore":6,"stat.mineBlock.mysticalagriculture.prosperity_ore":3,"stat.killEntity.Zombie":75,"stat.pickup.minecraft.snowball":85,"stat.craftItem.minecraft.dye":105,"stat.mineBlock.tp.maloberry_bush":1,"stat.pickup.croparia.seed_crop_iron":10,"stat.useItem.tconstruct.hammer":9946,"stat.pickup.iceandfire.troll_weapon.trunk":2,"stat.mineBlock.minecraft.gold_ore":10,"stat.craftItem.minecraft.slime_ball":4,"stat.diveOneCm":120870,"stat.mineBlock.biomesoplenty.coral":1,"stat.pickup.minecraft.wheat":8,"stat.pickup.croparia.fruit_redstone":20,"stat.pickup.tconstruct.tooltables":5,"stat.pickup.iceandfire.dragonscales_white":8,"stat.mineBlock.minecraft.mossy_cobblestone":1,"stat.drop.improvableskills.skills_book":1,"stat.pickup.iceandfire.dragonscales_bronze":10,"stat.pickup.croparia.fruit_gold":17,"stat.mineBlock.tconstruct.slime_leaves":1,"stat.pickup.minecraft.obsidian":12,"stat.drop.extrautils2.goldenlasso":4,"stat.jump":20513,"stat.pickup.harvestcraft.bananaitem":2,"stat.pickup.minecraft.coal":102,"stat.pickup.minecraft.iron_ingot":11,"stat.pickup.tconstruct.seared_tank":3,"stat.mineBlock.fossil.fossil":226,"stat.craftItem.minecraft.lever":1,"stat.drop.minecraft.diamond_sword":1,"stat.craftItem.rustic.crop_stake":3,"stat.pickup.minecraft.gunpowder":20,"stat.craftItem.minecraft.torch":180,"stat.pickup.minecraft.dirt":2878,"stat.drop.minecraft.iron_shovel":1,"stat.useItem.chisel.quartz1":1146,"stat.drop.minecraft.glowstone":32,"stat.pickup.iceandfire.fire_dragon_heart":2,"stat.mineBlock.minecraft.lapis_ore":7,"stat.pickup.minecraft.red_sandstone":2,"stat.pickup.rustic.wind_thistle":1,"stat.craftItem.croparia.seed_crop_gold":1,"stat.mineBlock.minecraft.glass_pane":14,"stat.damageTaken":35716,"stat.craftItem.extrautils2.goldenlasso":4,"stat.mineBlock.torchmaster.mega_torch":16,"stat.killEntity.tconstruct.blueslime":16,"stat.mineBlock.minecraft.red_flower":3,"stat.mineBlock.minecraft.torch":58,"stat.pickup.minecraft.log2":61,"stat.pickup.ebwizardry.crystal_flower":1,"stat.craftItem.minecraft.glowstone":16,"stat.pickup.minecraft.bed":3,"stat.pickup.tconstruct.ingots":1,"stat.pickup.minecraft.concrete":34,"stat.killEntity.hippogryph":2,"stat.mineBlock.taiga.tiberium_ore":30,"stat.pickup.minecraft.quartz_block":65,"stat.pickup.minecraft.potato":14,"stat.useItem.forge.bucketfilled":7,"stat.entityKilledBy.Zombie":9,"stat.pickup.harvestcraft.lettuceitem":8,"stat.useItem.harvestcraft.onionitem":1,"stat.craftItem.securitycraft.universal_block_reinforcer_lvl1":1,"stat.useItem.tconstruct.shovel":13798,"stat.useItem.minecraft.chest":3,"stat.craftItem.extrautils2.teleporter":1,"stat.useItem.minecraft.lava_bucket":17,"stat.mineBlock.biomesoplenty.planks_0":4,"stat.drop.minecraft.netherrack":64,"stat.useItem.tconstruct.faucet":7,"stat.useItem.tconstruct.lavawood_stairs":5,"stat.useItem.securitycraft.reinforced_stone_brick":128,"stat.useItem.tombstone.gift":4,"stat.pickup.harvestcraft.spiceleafitem":6,"stat.killEntity.if_troll":2,"stat.pickup.scalinghealth.heartcontainer":3,"stat.mineBlock.scalinghealth.crystalore":5,"stat.pickup.minecraft.ender_pearl":1,"stat.drop.minecraft.egg":1,"stat.craftItem.tconstruct.firewood":8,"stat.useItem.minecraft.concrete":1,"stat.useItem.minecraft.netherrack":23,"stat.craftItem.travelersbackpack.sleeping_bag_bottom":1,"stat.craftItem.minecraft.stained_glass_pane":80,"stat.pickup.biomesoplenty.gem":4,"stat.craftItem.minecraft.bookshelf":1,"stat.mineBlock.minecraft.stonebrick":20,"stat.craftItem.extrautils2.angelring":2,"stat.pickup.harvestcraft.queenbeeitem":1,"stat.pickup.harvestcraft.cucumberitem":8,"stat.pickup.harvestcraft.strawberryitem":9,"stat.mineBlock.minecraft.glowstone":26,"stat.pickup.minecraft.dark_oak_stairs":1,"stat.mineBlock.tconstruct.seared_slab":5,"stat.mobKills":243,"stat.mineBlock.minecraft.bookshelf":38,"stat.mineBlock.taiga.dilithium_ore":1,"stat.drop.flammpfeil.slashblade.proudsoul":2,"stat.pickup.iceandfire.gorgon_head":1,"stat.pickup.minecraft.diamond":5,"stat.pickup.minecraft.torch":83,"stat.killEntity.firedragon":1,"stat.drop.culinaryconstruct.sandwich":44,"stat.pickup.tconstruct.book":1,"stat.mineBlock.tconstruct.seared_tank":4,"stat.mineBlock.ebwizardry.crystal_flower":1,"stat.killEntity.Blaze":4,"stat.useItem.minecraft.planks":2232,"stat.drop.tconstruct.pickaxe":3,"stat.pickup.tp.raspberry_berry":1,"stat.drop.harvestcraft.plumitem":1,"stat.useItem.minecraft.nether_brick_stairs":5,"stat.pickup.minecraft.glowstone_dust":139,"stat.drop.tconstruct.slime_boots":1,"stat.pickup.minecraft.porkchop":1,"stat.useItem.thermalfoundation.ore":7,"stat.drop.ebwizardry.magic_crystal":1,"stat.drop.travelersbackpack.travelers_backpack":1,"stat.mineBlock.minecraft.nether_brick_fence":2,"stat.pickup.minecraft.sand":76,"stat.entityKilledBy.Spider":4,"stat.pickup.minecraft.hardened_clay":2,"stat.mineBlock.rustic.beehive":1,"stat.pickup.iceandfire.troll_leather_forest":5,"stat.pickup.fossil.bone_leg_bone":2,"stat.killEntity.icedragon":1,"stat.mineBlock.tp.ender_ore":1,"stat.craftItem.minecraft.stone_sword":1,"stat.mineBlock.fossil.iced_stone":85,"stat.pickup.fossil.tar_fossil":1,"stat.mineBlock.minecraft.snow_layer":6,"stat.entityKilledBy.firedragon":6,"stat.mineBlock.minecraft.sand":133,"stat.mineBlock.biomesoplenty.ash_block":49,"stat.craftItem.extrautils2.resonator":1,"stat.craftItem.minecraft.blaze_powder":18,"stat.pickup.tconstruct.slime_sapling":2,"stat.drop.minecraft.diamond":3,"stat.mineBlock.tconstruct.slime_grass_tall":2,"stat.mineBlock.mysticalagriculture.soulstone":227,"stat.craftItem.minecraft.hardened_clay":2,"stat.mineBlock.minecraft.dark_oak_stairs":1,"stat.craftItem.minecraft.pumpkin_seeds":32,"stat.pickup.iceandfire.dragon_skull":2,"stat.mineBlock.taiga.karmesine_ore":3,"stat.useItem.minecraft.dark_oak_stairs":75,"stat.useItem.extrautils2.teleporter":1,"stat.drop.minecraft.stone_slab":1,"stat.pickup.croparia.seed_crop_redstone":26,"stat.useItem.extrautils2.pipe":7,"stat.pickup.minecraft.furnace":2,"stat.mineBlock.tconstruct.seared_stairs_brick":34,"stat.pickup.tconstruct.cast":8,"stat.mineBlock.harvestcraft.windygarden":147,"stat.craftItem.travelersbackpack.travelers_backpack":1,"stat.pickup.minecraft.skull":2,"stat.pickup.tombstone.magic_scroll":5,"stat.mineBlock.extrautils2.passivegenerator":4,"stat.drop.flammpfeil.slashblade.slashbladenamed":1,"stat.craftItem.mysticalagriculture.storage":3,"stat.craftItem.ironchest.iron_chest":4,"stat.pickup.tconstruct.slime_dirt":20,"stat.mineBlock.minecraft.soul_sand":17,"stat.drop.taiga.tiberium_crystal":1,"stat.drop.biomesoplenty.biome_finder":2,"stat.pickup.fossil.broken_helmet":1,"stat.drop.extrautils2.passivegenerator":8,"stat.playOneMinute":2257987,"stat.useItem.rustic.fertile_soil":30,"stat.pickup.minecraft.blaze_rod":1,"stat.drop.minecraft.chest":19,"stat.pickup.minecraft.iron_bars":39,"stat.pickup.rustic.aloe_vera":2,"stat.pickup.minecraft.netherrack":767,"stat.useItem.croparia.fruit_iron":1,"stat.pickup.minecraft.pumpkin":8,"stat.mineBlock.torcherino.blockdoublecompressedtorcherino":29,"stat.pickup.tconstruct.casting":9,"stat.mineBlock.minecraft.netherrack":3560,"stat.mineBlock.minecraft.ice":1,"stat.drop.extrautils2.decorativesolidwood":1,"stat.mineBlock.rustic.slate":94,"stat.mineBlock.tconstruct.faucet":5,"stat.fallOneCm":367422,"stat.drop.minecraft.stone":9,"stat.pickup.tp.pouch":426,"stat.mineBlock.rustic.horsetail":1,"stat.craftItem.tconstruct.toolforge":1,"stat.pickup.croparia.seed_crop_diamond":7,"stat.pickup.taiga.meteoritecobble_block":8,"stat.craftItem.minecraft.chest":14,"stat.pickup.minecraft.red_mushroom":2,"stat.useItem.torcherino.blockdoublecompressedtorcherino":30,"stat.pickup.fossil.bone_ribcage":2,"stat.pickup.minecraft.feather":3,"stat.mineBlock.minecraft.red_nether_brick":8,"stat.pickup.rustic.tomato":2,"stat.craftItem.tconstruct.materials":61,"stat.craftItem.extrautils2.ingredients":3,"stat.pickup.tconstruct.seared_stairs_brick":40,"stat.pickup.rustic.fertile_soil":21,"stat.mineBlock.minecraft.snow":116,"stat.pickup.tconstruct.large_sword_blade":1,"stat.mineBlock.minecraft.gravel":156,"stat.useItem.minecraft.stone_pickaxe":218,"stat.craftItem.tconstruct.seared_tank":2,"stat.drop.tconstruct.seared":1,"stat.useItem.croparia.seed_crop_coal":6,"stat.useItem.minecraft.stone_sword":103,"stat.mineBlock.rustic.aloe_vera":1,"stat.useItem.harvestcraft.cherryitem":1,"stat.useItem.biomesoplenty.berries":4,"stat.useItem.minecraft.iron_bars":1,"stat.drop.minecraft.iron_axe":1,"stat.pickup.rustic.bee":2,"stat.useItem.minecraft.torch":627,"stat.pickup.flammpfeil.slashblade.proudsoul":2,"stat.pickup.tp.wub_gem":19,"stat.useItem.extrautils2.grocket":5,"stat.craftItem.minecraft.redstone_block":1,"stat.useItem.ironchest.iron_chest":11,"stat.pickup.minecraft.crafting_table":8,"stat.pickup.biomesoplenty.coral":1,"stat.useItem.minecraft.log":109,"stat.pickup.tp.plump_pear":1,"stat.craftItem.minecraft.crafting_table":12,"stat.drop.ironchest.iron_chest":2,"stat.drop.biomesoplenty.coral":1,"stat.pickup.minecraft.iron_hoe":1,"stat.pickup.tconstruct.lavawood_stairs":2,"stat.killEntity.LavaSlime":2,"stat.mineBlock.ebwizardry.crystal_ore":38,"stat.pickup.extrautils2.grocket":8,"stat.pickup.minecraft.log":427,"stat.useItem.minecraft.cooked_fish":12,"stat.pickup.thermalfoundation.tool.hammer_diamond":1,"stat.pickup.croparia.fruit_lapis":15,"stat.mineBlock.rustic.fertile_soil":22,"stat.pickup.biomesoplenty.planks_0":4,"stat.pickup.minecraft.chainmail_leggings":1,"stat.pickup.minecraft.sapling":159,"stat.entityKilledBy.Enderman":2,"stat.drop.minecraft.clay":4,"stat.craftItem.tconstruct.smeltery_controller":1,"stat.pickup.harvestcraft.parsnipitem":1,"stat.mineBlock.iceandfire.goldpile":18,"stat.pickup.rustic.crop_stake":2,"stat.mineBlock.tconstruct.toolforge":1,"stat.mineBlock.tconstruct.slime_grass":18,"stat.mineBlock.taiga.jauxum_ore":1,"stat.useItem.croparia.fruit_coal":1,"stat.useItem.biomesoplenty.biome_block":149,"stat.killEntity.WitherSkeleton":4,"stat.pickup.croparia.seed_crop_lapis":15,"stat.pickup.harvestcraft.juteitem":2,"stat.pickup.tconstruct.slime_boots":2,"stat.craftItem.croparia.seed_crop_lapis":1,"stat.drop.tconstruct.hatchet":1,"stat.sneakTime":86482,"stat.pickup.harvestcraft.tealeafitem":2,"stat.pickup.rustic.chili_pepper_seeds":55,"stat.pickup.minecraft.rabbit":1,"stat.pickup.minecraft.stone_slab":11,"stat.pickup.minecraft.yellow_flower":6,"stat.mineBlock.chisel.quartz1":483,"stat.pickup.croparia.fruit_diamond":9,"stat.pickup.minecraft.chest":19,"stat.drop.minecraft.stone_pickaxe":1,"stat.useItem.mysticalagriculture.tier1_inferium_seeds":7,"stat.pickup.minecraft.bone":46,"stat.useItem.minecraft.log2":40,"stat.useItem.minecraft.diamond_sword":12,"stat.craftItem.tconstruct.slimesling":1,"stat.craftItem.extrautils2.compressedcobblestone":10,"stat.swimOneCm":170342,"stat.climbOneCm":2008,"stat.pickup.harvestcraft.artichokeitem":9,"stat.craftItem.minecraft.gold_block":5,"stat.useItem.minecraft.dirt":5527,"stat.pickup.croparia.fruit_coal":32,"stat.pickup.warpbook.boundwarppage":4,"stat.mineBlock.biomesoplenty.biome_block":151,"stat.mineBlock.extrautils2.teleporter":1,"stat.pickup.minecraft.anvil":1,"stat.craftItem.minecraft.stone_pickaxe":2,"stat.pickup.taiga.karmesine_ore":1,"stat.mineBlock.minecraft.magma":47,"stat.pickup.minecraft.cobblestone":4068,"stat.mineBlock.biomesoplenty.double_plant":10,"stat.craftItem.croparia.seed_crop_rawbeef":1,"stat.useItem.minecraft.stone_shovel":18,"stat.mineBlock.chisel.limestone2":25,"stat.pickup.minecraft.clay":2,"stat.drop.minecraft.wheat_seeds":2,"stat.craftItem.minecraft.wooden_slab":6,"stat.pickup.harvestcraft.leekitem":3,"stat.pickup.minecraft.redstone":154,"stat.mineBlock.minecraft.iron_ore":99,"stat.craftItem.minecraft.book":1,"stat.drop.biomesoplenty.biome_essence":2,"stat.drop.minecraft.log":2,"stat.pickup.fossil.plant_fossil":32,"stat.pickup.minecraft.mutton":27,"stat.drop.rustic.chili_pepper_seeds":8,"stat.mineBlock.ebwizardry.arcane_workbench":1,"stat.mineBlock.biomesoplenty.log_3":2,"stat.craftItem.torchmaster.mega_torch":2,"stat.mineBlock.minecraft.coal_block":1,"stat.pickup.minecraft.dark_oak_door":2,"stat.mineBlock.thermalfoundation.ore":212,"stat.pickup.minecraft.stonebrick":27,"stat.drop.extrautils2.ingredients":2,"stat.drop.minecraft.dirt":131,"stat.pickup.minecraft.iron_shovel":2,"stat.pickup.ebwizardry.magic_crystal":68,"stat.pickup.tconstruct.seared_slab":5,"stat.mineBlock.minecraft.nether_brick":144,"stat.mineBlock.minecraft.red_sandstone_stairs":1,"stat.craftItem.tconstruct.soil":56,"stat.pickup.tconstruct.smeltery_controller":2,"stat.craftItem.tconstruct.slime_boots":3,"stat.craftItem.minecraft.stone_slab2":56,"stat.pickup.chisel.planks-dark-oak":4,"stat.drop.rustic.tomato_seeds":2,"stat.pickup.improvableskills.scroll_normal":2,"stat.craftItem.minecraft.stick":120,"stat.useItem.extrautils2.passivegenerator":7,"stat.useItem.minecraft.stone_slab":1,"stat.drop.croparia.fruit_coal":1,"stat.pickup.extrautils2.teleporter":1,"stat.drop.croparia.seed_crop_iron":1,"stat.craftItem.minecraft.stone":21,"stat.craftItem.minecraft.gold_nugget":18,"stat.pickup.harvestcraft.barleyitem":7,"stat.useItem.tconstruct.casting":6,"stat.mineBlock.minecraft.crafting_table":8,"stat.useItem.minecraft.diamond_pickaxe":625,"stat.useItem.minecraft.carrot":9,"stat.drop.iceandfire.fire_dragon_flesh":1,"stat.pickup.minecraft.diamond_chestplate":1,"stat.entityKilledBy.Creeper":2,"stat.useItem.extrautils2.itembuilderswand":1586,"stat.useItem.extrautils2.crafter":5,"stat.killEntity.ebwizardry:wizard":1,"stat.mineBlock.minecraft.planks":131,"stat.drop":165,"stat.craftItem.croparia.seed_crop_iron":1,"stat.killEntity.Sheep":17,"stat.useItem.tconstruct.seared":5964,"stat.craftItem.minecraft.diamond_pickaxe":1,"stat.mineBlock.mysticalagriculture.nether_inferium_ore":9,"stat.craftItem.securitycraft.universal_block_remover":1,"stat.craftItem.minecraft.clay":13,"stat.pickup.harvestcraft.garlicitem":1,"stat.pickup.rustic.wildberry_bush":16,"stat.pickup.tconstruct.toolforge":1,"stat.useItem.tconstruct.firewood_stairs":5,"stat.drop.minecraft.wooden_pickaxe":2,"stat.pickup.fossil.iced_meat":5,"stat.pickup.minecraft.gravel":104,"stat.craftItem.tp.pouch":3,"stat.useItem.minecraft.diamond_axe":13,"stat.mineBlock.minecraft.anvil":1,"stat.mineBlock.tconstruct.smeltery_controller":2,"stat.pickup.extrautils2.goldenlasso":2,"stat.useItem.croparia.fruit_gold":1,"stat.mineBlock.tconstruct.slime_dirt":3,"stat.pickup.tconstruct.sharpening_kit":1,"stat.pickup.harvestcraft.dragonfruititem":4,"stat.useItem.minecraft.stained_glass_pane":93,"stat.craftItem.travelersbackpack.backpack_tank":4,"stat.pickup.minecraft.iron_helmet":3,"stat.pickup.scalinghealth.crystalshard":5,"stat.useItem.minecraft.stone_axe":98,"stat.pickup.harvestcraft.peanutitem":1,"stat.mineBlock.harvestcraft.shadedgarden":8,"stat.pickup.minecraft.spider_eye":8,"stat.pickup.harvestcraft.bellpepperitem":2,"stat.craftItem.tconstruct.book":1,"stat.drop.minecraft.bed":1,"stat.useItem.minecraft.cooked_chicken":3,"stat.pickup.minecraft.iron_ore":8,"stat.pickup.tconstruct.slime_congealed":25,"stat.craftItem.extrautils2.chickenring":2,"stat.mineBlock.minecraft.iron_bars":19,"stat.drop.chiselsandbits.tape_measure":1,"stat.craftItem.minecraft.flint_and_steel":1,"stat.pickup.rustic.tomato_seeds":55,"stat.mineBlock.tconstruct.tooltables":5,"stat.pickup.minecraft.leaves":44,"stat.mineBlock.tp.raspberry_bush":1,"stat.pickup.taiga.dilithium_crystal":2,"stat.pickup.minecraft.leather":8,"stat.mineBlock.minecraft.furnace":2,"stat.useItem.minecraft.wooden_pickaxe":4,"stat.mineBlock.extrautils2.user":1,"stat.pickup.mysticalagriculture.crafting":543,"stat.pickup.minecraft.reeds":21,"stat.killEntity.CaveSpider":2,"stat.pickup.taiga.tiberium_crystal":5,"tombstone:undead_killed":123,"stat.useItem.tombstone.grave_key":4,"stat.craftItem.croparia.seed_crop_diamond":1,"stat.pickup.tconstruct.materials":28,"stat.mineBlock.taiga.ovium_ore":1,"stat.pickup.croparia.seed_crop_gold":10,"stat.damageDealt":68937,"stat.craftItem.minecraft.glass":1,"stat.sleepInBed":11,"stat.mineBlock.minecraft.nether_brick_stairs":1,"stat.pickup.croparia.fruit_iron":12,"stat.killEntity.Cow":2,"stat.mineBlock.mysticalagriculture.nether_prosperity_ore":14,"stat.useItem.minecraft.crafting_table":1,"stat.killEntity.Pig":2,"stat.pickup.harvestcraft.elderberryitem":6,"stat.craftItem.minecraft.stone_shovel":1,"stat.walkOneCm":7012318,"stat.useItem.croparia.fruit_diamond":1,"stat.playerKills":30,"stat.craftItem.torcherino.blockcompressedtorcherino":21,"stat.pickup.minecraft.stick":15,"stat.useItem.tconstruct.seared_slab":5,"stat.pickup.minecraft.clay_ball":125,"stat.pickup.securitycraft.reinforced_stone_brick":32,"stat.drop.croparia.fruit_iron":1,"stat.mineBlock.chisel.basalt2":11,"stat.drop.croparia.seed_crop_redstone":3,"stat.entityKilledBy.ebwizardry:ice_wraith":1,"stat.pickup.minecraft.stone":1498,"stat.mineBlock.minecraft.wool":2,"stat.pickup.harvestcraft.zucchiniitem":2,"stat.pickup.chisel.quartz1":775,"stat.mineBlock.minecraft.packed_ice":5,"stat.useItem.minecraft.leaves":161,"stat.useItem.torchmaster.mega_torch":3,"stat.pickup.minecraft.gold_ingot":13,"stat.pickup.taiga.ovium_ore":1,"stat.killEntity.Skeleton":35,"stat.pickup.biomesoplenty.log_3":1,"stat.pickup.harvestcraft.amaranthitem":4,"stat.mineBlock.tp.wub_ore":16,"stat.craftItem.morebuckets.diamond_bucket":3,"stat.killEntity.Chicken":5,"stat.pickup.minecraft.netherbrick":388,"stat.killEntity.Spider":21,"stat.mineBlock.minecraft.quartz_ore":36,"stat.pickup.minecraft.bread":24,"stat.useItem.rustic.crop_stake":2,"stat.pickup.minecraft.quartz":34,"stat.pickup.harvestcraft.plumitem":2,"stat.craftItem.culinaryconstruct.sandwich_station":1,"stat.pickup.mysticalagriculture.soulstone":87,"stat.mineBlock.minecraft.leaves":2663,"stat.mineBlock.tconstruct.seared":621,"stat.mineBlock.minecraft.redstone_ore":97,"stat.mineBlock.tconstruct.casting":11,"stat.mineBlock.tp.water_block":1,"stat.craftItem.minecraft.coal_block":1,"stat.mineBlock.minecraft.stone":25576,"stat.drop.tconstruct.book":2,"stat.useItem.tconstruct.hatchet":3643,"stat.useItem.minecraft.sandstone":2}